recentearthquake/__init__.py
latest_earthquake_in_indonesia-0.5.dist-info/LICENSE
latest_earthquake_in_indonesia-0.5.dist-info/METADATA
latest_earthquake_in_indonesia-0.5.dist-info/WHEEL
latest_earthquake_in_indonesia-0.5.dist-info/top_level.txt
latest_earthquake_in_indonesia-0.5.dist-info/RECORD
