Metadata-Version: 2.1
Name: latest-earthquake-in-indonesia
Version: 0.5
Summary: This package about the last earthquake from BMKG Indonesia
Home-page: https://github.com/kuli-coding/last-indonesia-earthquake
Author: Rijaluddin
Author-email: ortonrko90900@gmail.com
License: UNKNOWN
Project-URL: Github, https://github.com/kuli-coding/last-indonesia-earthquake
Platform: UNKNOWN
Classifier: Programming Language :: Python :: 3
Classifier: License :: OSI Approved :: GNU General Public License v3 (GPLv3)
Classifier: Operating System :: OS Independent
Classifier: Development Status :: 5 - Production/Stable
Requires-Python: >=3.6
License-File: LICENSE
